ropt_nomad/__init__.py
ropt_nomad/nomad.py
ropt_nomad/py.typed
ropt_nomad/version.py
ropt_nomad-0.24.1.dist-info/licenses/LICENSE
ropt_nomad-0.24.1.dist-info/METADATA
ropt_nomad-0.24.1.dist-info/WHEEL
ropt_nomad-0.24.1.dist-info/entry_points.txt
ropt_nomad-0.24.1.dist-info/top_level.txt
ropt_nomad-0.24.1.dist-info/RECORD
