Metadata-Version: 2.4
Name: ropt-nomad
Version: 0.24.1
Summary: A NOMAD plugin for the ropt robust optimization package
Project-URL: Homepage, https://github.com/TNO-ropt/ropt-nomad
Project-URL: Repository, https://github.com/TNO-ropt/ropt-nomad
Project-URL: Bug Tracker, https://github.com/TNO-ropt/ropt-nomad/issues
Classifier: Development Status :: 4 - Beta
Classifier: License :: OSI Approved :: GNU General Public License v3 (GPLv3)
Classifier: Natural Language :: English
Classifier: Programming Language :: Python
Classifier: Programming Language :: Python :: 3.11
Classifier: Programming Language :: Python :: 3.12
Classifier: Programming Language :: Python :: 3.13
Classifier: Topic :: Scientific/Engineering
Requires-Python: >=3.11
License-File: LICENSE
Requires-Dist: PyNomadBBO
Dynamic: license-file
